GroovyRumen/README.md
GroovyRumen/__init__.py
GroovyRumen/__main__.py
GroovyRumen/file.epub
GroovyRumen/index.html
GroovyRumen/css/__init__.py
GroovyRumen/css/annotations.css
GroovyRumen/css/main.css
GroovyRumen/css/normalize.css
GroovyRumen/css/popup.css
GroovyRumen/font/__init__.py
GroovyRumen/font/fontello.eot
GroovyRumen/font/fontello.svg
GroovyRumen/font/fontello.ttf
GroovyRumen/font/fontello.woff
GroovyRumen/img/__init__.py
GroovyRumen/img/annotator-glyph-sprite.png
GroovyRumen/img/annotator-icon-sprite.png
GroovyRumen/img/apple-touch-icon.png
GroovyRumen/img/cancelfullscreen.png
GroovyRumen/img/close.png
GroovyRumen/img/fullscreen.png
GroovyRumen/img/loader.gif
GroovyRumen/img/menu-icon.png
GroovyRumen/img/save.png
GroovyRumen/img/saved.png
GroovyRumen/img/settings-s.png
GroovyRumen/img/settings.png
GroovyRumen/img/star.png
GroovyRumen/js/__init__.py
GroovyRumen/js/epub.js
GroovyRumen/js/epub.min.js
GroovyRumen/js/epub.min.map
GroovyRumen/js/hooks.min.js
GroovyRumen/js/hooks.min.map
GroovyRumen/js/reader.js
GroovyRumen/js/reader.js.map
GroovyRumen/js/reader.min.js
GroovyRumen/js/reader.min.map
GroovyRumen/js/hooks/__init__.py
GroovyRumen/js/hooks/extensions/__init__.py
GroovyRumen/js/hooks/extensions/highlight.js
GroovyRumen/js/libs/__init__.py
GroovyRumen/js/libs/jquery.min.js
GroovyRumen/js/libs/localforage.min.js
GroovyRumen/js/libs/screenfull.js
GroovyRumen/js/libs/screenfull.min.js
GroovyRumen/js/libs/zip.min.js
GroovyRumen/js/plugins/__init__.py
GroovyRumen/js/plugins/hypothesis.js
GroovyRumen/js/plugins/search.js
groovy_rumen-2024.3.4.0.dist-info/METADATA
groovy_rumen-2024.3.4.0.dist-info/WHEEL
groovy_rumen-2024.3.4.0.dist-info/entry_points.txt
groovy_rumen-2024.3.4.0.dist-info/top_level.txt
groovy_rumen-2024.3.4.0.dist-info/RECORD
